mhai/__init__.py
mhai/mhai.py
mhai/py.typed
mhai-0.1.0.dist-info/LICENSE
mhai-0.1.0.dist-info/METADATA
mhai-0.1.0.dist-info/WHEEL
mhai-0.1.0.dist-info/RECORD
