Metadata-Version: 2.3
Name: mhai
Version: 0.1.0
Summary: This Project aims to ...
License: BSD 3 Clause
Author: Ivan Ogasawara
Author-email: ivan.ogasawara@gmail.com
Requires-Python: >=3.9,<4
Classifier: License :: Other/Proprietary License
Classifier: Programming Language :: Python :: 3
Classifier: Programming Language :: Python :: 3.9
Classifier: Programming Language :: Python :: 3.10
Classifier: Programming Language :: Python :: 3.11
Classifier: Programming Language :: Python :: 3.12
Classifier: Programming Language :: Python :: 3.13
